[
    {"mime": "application/postscript", "extention": "ai"},
    {"mime": "audio/x-aiff", "extention": "aif"},
    {"mime": "audio/x-aiff", "extention": "aifc"},
    {"mime": "audio/x-aiff", "extention": "aiff"},
    {"mime": "text/plain", "extention": "asc"},
    {"mime": "application/atom+xml", "extention": "atom"},
    {"mime": "audio/basic", "extention": "au"},
    {"mime": "video/x-msvideo", "extention": "avi"},
    {"mime": "application/x-bcpio", "extention": "bcpio"},
    {"mime": "application/octet-stream", "extention": "bin"},
    {"mime": "application/octet-stream", "extention": "cnf"},
    {"mime": "image/bmp", "extention": "bmp"},
    {"mime": "application/x-netcdf", "extention": "cdf"},
    {"mime": "image/cgm", "extention": "cgm"},
    {"mime": "application/octet-stream", "extention": "class"},
    {"mime": "application/x-cpio", "extention": "cpio"},
    {"mime": "application/mac-compactpro", "extention": "cpt"},
    {"mime": "application/x-csh", "extention": "csh"},
    {"mime": "text/css", "extention": "css"},
    {"mime": "text/csv", "extention": "csv"},
    {"mime": "application/x-director", "extention": "dcr"},
    {"mime": "video/x-dv", "extention": "dif"},
    {"mime": "application/x-director", "extention": "dir"},
    {"mime": "image/vnd.djvu", "extention": "djv"},
    {"mime": "image/vnd.djvu", "extention": "djvu"},
    {"mime": "application/octet-stream", "extention": "dll"},
    {"mime": "application/octet-stream", "extention": "dmg"},
    {"mime": "application/octet-stream", "extention": "dms"},
    {"mime": "application/msword", "extention": "doc"},
    {"mime": "application/xml-dtd", "extention": "dtd"},
    {"mime": "video/x-dv", "extention": "dv"},
    {"mime": "application/x-dvi", "extention": "dvi"},
    {"mime": "application/x-director", "extention": "dxr"},
    {"mime": "application/postscript", "extention": "eps"},
    {"mime": "text/x-setext", "extention": "etx"},
    {"mime": "application/octet-stream", "extention": "exe"},
    {"mime": "application/andrew-inset", "extention": "ez"},
    {"mime": "image/gif", "extention": "gif"},
    {"mime": "application/srgs", "extention": "gram"},
    {"mime": "application/srgs+xml", "extention": "grxml"},
    {"mime": "application/x-gtar", "extention": "gtar"},
    {"mime": "application/x-hdf", "extention": "hdf"},
    {"mime": "application/mac-binhex40", "extention": "hqx"},
    {"mime": "text/html", "extention": "htm"},
    {"mime": "text/html", "extention": "html"},
    {"mime": "x-conference/x-cooltalk", "extention": "ice"},
    {"mime": "image/x-icon", "extention": "ico"},
    {"mime": "text/calendar", "extention": "ics"},
    {"mime": "image/ief", "extention": "ief"},
    {"mime": "text/calendar", "extention": "ifb"},
    {"mime": "model/iges", "extention": "iges"},
    {"mime": "model/iges", "extention": "igs"},
    {"mime": "application/x-java-jnlp-file", "extention": "jnlp"},
    {"mime": "image/jp2", "extention": "jp2"},
    {"mime": "image/jpeg", "extention": "jpe"},
    {"mime": "image/jpeg", "extention": "jpeg"},
    {"mime": "image/jpeg", "extention": "jpg"},
    {"mime": "application/x-javascript", "extention": "js"},
    {"mime": "audio/midi", "extention": "kar"},
    {"mime": "application/x-latex", "extention": "latex"},
    {"mime": "application/octet-stream", "extention": "lha"},
    {"mime": "application/octet-stream", "extention": "lzh"},
    {"mime": "audio/x-mpegurl", "extention": "m3u"},
    {"mime": "audio/mp4a-latm", "extention": "m4a"},
    {"mime": "audio/mp4a-latm", "extention": "m4b"},
    {"mime": "audio/mp4a-latm", "extention": "m4p"},
    {"mime": "video/vnd.mpegurl", "extention": "m4u"},
    {"mime": "video/x-m4v", "extention": "m4v"},
    {"mime": "image/x-macpaint", "extention": "mac"},
    {"mime": "application/x-troff-man", "extention": "man"},
    {"mime": "application/mathml+xml", "extention": "mathml"},
    {"mime": "application/x-troff-me", "extention": "me"},
    {"mime": "model/mesh", "extention": "mesh"},
    {"mime": "audio/midi", "extention": "mid"},
    {"mime": "audio/midi", "extention": "midi"},
    {"mime": "application/vnd.mif", "extention": "mif"},
    {"mime": "video/quicktime", "extention": "mov"},
    {"mime": "video/x-sgi-movie", "extention": "movie"},
    {"mime": "audio/mpeg", "extention": "mp2"},
    {"mime": "audio/mpeg", "extention": "mp3"},
    {"mime": "video/mp4", "extention": "mp4"},
    {"mime": "video/mpeg", "extention": "mpe"},
    {"mime": "video/mpeg", "extention": "mpeg"},
    {"mime": "video/mpeg", "extention": "mpg"},
    {"mime": "audio/mpeg", "extention": "mpga"},
    {"mime": "application/x-troff-ms", "extention": "ms"},
    {"mime": "model/mesh", "extention": "msh"},
    {"mime": "video/vnd.mpegurl", "extention": "mxu"},
    {"mime": "application/x-netcdf", "extention": "nc"},
    {"mime": "application/oda", "extention": "oda"},
    {"mime": "application/ogg", "extention": "ogg"},
    {"mime": "image/x-portable-bitmap", "extention": "pbm"},
    {"mime": "image/pict", "extention": "pct"},
    {"mime": "chemical/x-pdb", "extention": "pdb"},
    {"mime": "application/pdf", "extention": "pdf"},
    {"mime": "image/x-portable-graymap", "extention": "pgm"},
    {"mime": "application/x-chess-pgn", "extention": "pgn"},
    {"mime": "image/pict", "extention": "pic"},
    {"mime": "image/pict", "extention": "pict"},
    {"mime": "image/png", "extention": "png"},
    {"mime": "image/x-portable-anymap", "extention": "pnm"},
    {"mime": "image/x-macpaint", "extention": "pnt"},
    {"mime": "image/x-macpaint", "extention": "pntg"},
    {"mime": "image/x-portable-pixmap", "extention": "ppm"},
    {"mime": "application/vnd.ms-powerpoint", "extention": "ppt"},
    {"mime": "application/postscript", "extention": "ps"},
    {"mime": "video/quicktime", "extention": "qt"},
    {"mime": "image/x-quicktime", "extention": "qti"},
    {"mime": "image/x-quicktime", "extention": "qtif"},
    {"mime": "audio/x-pn-realaudio", "extention": "ra"},
    {"mime": "audio/x-pn-realaudio", "extention": "ram"},
    {"mime": "image/x-cmu-raster", "extention": "ras"},
    {"mime": "application/rdf+xml", "extention": "rdf"},
    {"mime": "image/x-rgb", "extention": "rgb"},
    {"mime": "application/vnd.rn-realmedia", "extention": "rm"},
    {"mime": "application/x-troff", "extention": "roff"},
    {"mime": "text/rtf", "extention": "rtf"},
    {"mime": "text/richtext", "extention": "rtx"},
    {"mime": "text/sgml", "extention": "sgm"},
    {"mime": "text/sgml", "extention": "sgml"},
    {"mime": "application/x-sh", "extention": "sh"},
    {"mime": "application/x-shar", "extention": "shar"},
    {"mime": "model/mesh", "extention": "silo"},
    {"mime": "application/x-stuffit", "extention": "sit"},
    {"mime": "application/x-koan", "extention": "skd"},
    {"mime": "application/x-koan", "extention": "skm"},
    {"mime": "application/x-koan", "extention": "skp"},
    {"mime": "application/x-koan", "extention": "skt"},
    {"mime": "application/smil", "extention": "smi"},
    {"mime": "application/smil", "extention": "smil"},
    {"mime": "audio/basic", "extention": "snd"},
    {"mime": "application/octet-stream", "extention": "so"},
    {"mime": "application/x-futuresplash", "extention": "spl"},
    {"mime": "application/x-wais-source", "extention": "src"},
    {"mime": "application/x-sv4cpio", "extention": "sv4cpio"},
    {"mime": "application/x-sv4crc", "extention": "sv4crc"},
    {"mime": "image/svg+xml", "extention": "svg"},
    {"mime": "application/x-shockwave-flash", "extention": "swf"},
    {"mime": "application/x-troff", "extention": "t"},
    {"mime": "application/x-tar", "extention": "tar"},
    {"mime": "application/x-tcl", "extention": "tcl"},
    {"mime": "application/x-tex", "extention": "tex"},
    {"mime": "application/x-texinfo", "extention": "texi"},
    {"mime": "application/x-texinfo", "extention": "texinfo"},
    {"mime": "image/tiff", "extention": "tif"},
    {"mime": "image/tiff", "extention": "tiff"},
    {"mime": "application/x-troff", "extention": "tr"},
    {"mime": "text/tab-separated-values", "extention": "tsv"},
    {"mime": "text/plain", "extention": "txt"},
    {"mime": "application/x-ustar", "extention": "ustar"},
    {"mime": "application/x-cdlink", "extention": "vcd"},
    {"mime": "model/vrml", "extention": "vrml"},
    {"mime": "application/voicexml+xml", "extention": "vxml"},
    {"mime": "audio/x-wav", "extention": "wav"},
    {"mime": "image/vnd.wap.wbmp", "extention": "wbmp"},
    {"mime": "application/vnd.wap.wbxml", "extention": "wbmxl"},
    {"mime": "text/vnd.wap.wml", "extention": "wml"},
    {"mime": "application/vnd.wap.wmlc", "extention": "wmlc"},
    {"mime": "text/vnd.wap.wmlscript", "extention": "wmls"},
    {"mime": "application/vnd.wap.wmlscriptc", "extention": "wmlsc"},
    {"mime": "model/vrml", "extention": "wrl"},
    {"mime": "image/x-xbitmap", "extention": "xbm"},
    {"mime": "application/xhtml+xml", "extention": "xht"},
    {"mime": "application/xhtml+xml", "extention": "xhtml"},
    {"mime": "application/vnd.ms-excel", "extention": "xls"},
    {"mime": "application/vnd.ms-excel", "extention": "xlsx"},
    {"mime": "application/xml", "extention": "xml"},
    {"mime": "image/x-xpixmap", "extention": "xpm"},
    {"mime": "application/xml", "extention": "xsl"},
    {"mime": "application/xslt+xml", "extention": "xslt"},
    {"mime": "application/vnd.mozilla.xul+xml", "extention": "xul"},
    {"mime": "image/x-xwindowdump", "extention": "xwd"},
    {"mime": "chemical/x-xyz", "extention": "xyz"},
    {"mime": "application/zip", "extention": "zip"},
    {"mime": "application/rar", "extention": "rar"},
    {"mime": "text/plain", "extention": "rem"}
]
